sea.py
madtornado-0.3.9.data/scripts/sea.py
madtornado-0.3.9.dist-info/LICENSE
madtornado-0.3.9.dist-info/METADATA
madtornado-0.3.9.dist-info/WHEEL
madtornado-0.3.9.dist-info/entry_points.txt
madtornado-0.3.9.dist-info/top_level.txt
madtornado-0.3.9.dist-info/RECORD
