Metadata-Version: 2.1
Name: madtornado
Version: 0.3.9
Summary: Madtornado is a project templates for Tornado framework and quickly generate the Tornado project.
Home-page: https://github.com/SystemLight/madtornado
Author: SystemLight
Author-email: 1466335092@qq.com
Maintainer: SystemLight
Maintainer-email: 1466335092@qq.com
License: MIT
Download-URL: https://github.com/SystemLight/madtornado/releases
Keywords: tornado,web,http_server,mt,Mad_tornado,madtornado,Tornado project template,python3,sea,generate the Tornado project,tornado cli,tornado脚手架,生成tornado项目
Platform: Windows
Platform: Linux
Classifier: Development Status :: 3 - Alpha
Classifier: Intended Audience :: Developers
Classifier: Topic :: Software Development :: Build Tools
Classifier: License :: OSI Approved :: MIT License
Classifier: Programming Language :: Python :: 3.5
Classifier: Programming Language :: Python :: 3.6
Classifier: Programming Language :: Python :: 3.7
Classifier: Programming Language :: Python :: 3.8
Requires-Python: >=3.5
Requires-Dist: six (>=1.14.0)
Requires-Dist: tqdm (>=4.46.0)
Requires-Dist: greenlet (>=0.4.15)
Requires-Dist: PyJWT (>=1.7.1)
Requires-Dist: PyMySQL (>=0.9.3)
Requires-Dist: python-memcached (>=1.59)
Requires-Dist: tormysql (>=0.4.2)
Requires-Dist: tornado (>=6.0.4)
Requires-Dist: setuptools (>=46.1.3)
Requires-Dist: qrcode (>=6.1)
